<layouts>
    <layout id="MainLayout">
	    <drawable id="MoveReqIcon" />
	    <drawable id="LockedIcon" visible="false" />
	    <drawable id="UnlockedIcon" visible="false" />
	    <drawable id="MovingIcon" visible="false" />
	    <drawable id="UnknownIcon" />
        <drawable id="TaskCountIcon" class="TaskCountIcon" />
        <label id="NextUpdate" x="50%" y="9%" font="Gfx.FONT_TINY" color="Gfx.COLOR_WHITE" justification="Gfx.TEXT_JUSTIFY_CENTER" />
        <label id="Status" x="51%" y="77%" font="Gfx.FONT_MEDIUM" color="Gfx.COLOR_WHITE" justification="Gfx.TEXT_JUSTIFY_CENTER" />
        <label id="Error" x="51%" y="90%" font="Gfx.FONT_XTINY" color="Gfx.COLOR_RED" justification="Gfx.TEXT_JUSTIFY_CENTER" />
    </layout>
</layouts>